Trissotech/API.py
Trissotech/__init__.py
trissotech-0.0.6.dist-info/METADATA
trissotech-0.0.6.dist-info/WHEEL
trissotech-0.0.6.dist-info/licenses/LICENSE
trissotech-0.0.6.dist-info/RECORD
