Metadata-Version: 2.1
Name: Trissotech
Version: 0.0.6
Summary: Trissotech library
Project-URL: Homepage, https://www.trissotech.com/
Project-URL: Bug Tracker, https://www.facundonieto.com/contact
Author-email: Facu <facundonieto@mi.unc.edu.ar>
License-File: LICENSE
Classifier: License :: OSI Approved :: MIT License
Classifier: Operating System :: OS Independent
Classifier: Programming Language :: Python :: 3
Requires-Python: >=3.7
Requires-Dist: opencv-python
Requires-Dist: pillow
